[
    {
        "name": "InfStones",
        "rates": [
            {
                "epoch": 0,
                "pool_token_amount": "0",
                "sui_amount": "0"
            },
            {
                "epoch": 3,
                "pool_token_amount": "20000000000008650",
                "sui_amount": "20000000000432600"
            },
            {
                "epoch": 6,
                "pool_token_amount": "20000000000008817",
                "sui_amount": "20000000000441000"
            },
            {
                "epoch": 7,
                "pool_token_amount": "20000000000008902",
                "sui_amount": "20000000000445300"
            },
            {
                "epoch": 8,
                "pool_token_amount": "20000000000008987",
                "sui_amount": "20000000000449600"
            },
            {
                "epoch": 9,
                "pool_token_amount": "20000000000008987",
                "sui_amount": "20000000000449600"
            },
            {
                "epoch": 10,
                "pool_token_amount": "20000000000008987",
                "sui_amount": "20000000000449600"
            },
            {
                "epoch": 11,
                "pool_token_amount": "20000000000008987",
                "sui_amount": "20000000000449600"
            },
            {
                "epoch": 12,
                "pool_token_amount": "20000000000008987",
                "sui_amount": "20000000000449600"
            },
            {
                "epoch": 14,
                "pool_token_amount": "20000000000010533",
                "sui_amount": "20000000000527000"
            },
            {
                "epoch": 16,
                "pool_token_amount": "20000000000140348",
                "sui_amount": "20000000007017893"
            },
            {
                "epoch": 19,
                "pool_token_amount": "20000000000315481",
                "sui_amount": "20000000015774701"
            },
            {
                "epoch": 20,
                "pool_token_amount": "20000000000507924",
                "sui_amount": "20000000025396901"
            },
            {
                "epoch": 25,
                "pool_token_amount": "20010813621822648",
                "sui_amount": "20032783928569070"
            },
            {
                "epoch": 30,
                "pool_token_amount": "27005976303953287",
                "sui_amount": "27058544630409187"
            },
            {
                "epoch": 33,
                "pool_token_amount": "27006785076817543",
                "sui_amount": "27071668389919846"
            },
            {
                "epoch": 34,
                "pool_token_amount": "27007095025557223",
                "sui_amount": "27076081656889247"
            },
            {
                "epoch": 38,
                "pool_token_amount": "27008726686933403",
                "sui_amount": "27093446367041789"
            },
            {
                "epoch": 39,
                "pool_token_amount": "27009137753217744",
                "sui_amount": "27097561487443432"
            },
            {
                "epoch": 40,
                "pool_token_amount": "27009549590435460",
                "sui_amount": "27101675906840736"
            },
            {
                "epoch": 41,
                "pool_token_amount": "27009929442176529",
                "sui_amount": "27105758279645454"
            },
            {
                "epoch": 43,
                "pool_token_amount": "27010722885973152",
                "sui_amount": "27113957196175031"
            },
            {
                "epoch": 45,
                "pool_token_amount": "27011600164260913",
                "sui_amount": "27122239457980975"
            },
            {
                "epoch": 48,
                "pool_token_amount": "27012787936288320",
                "sui_amount": "27134534657711255"
            },
            {
                "epoch": 49,
                "pool_token_amount": "27013196781201883",
                "sui_amount": "27138646662868620"
            },
            {
                "epoch": 50,
                "pool_token_amount": "27013615985615512",
                "sui_amount": "27142768749228686"
            },
            {
                "epoch": 52,
                "pool_token_amount": "27013121537662841",
                "sui_amount": "27149673539686272"
            },
            {
                "epoch": 62,
                "pool_token_amount": "27018146187420046",
                "sui_amount": "27191038623148283"
            },
            {
                "epoch": 69,
                "pool_token_amount": "27020756381287328",
                "sui_amount": "27220072227376901"
            },
            {
                "epoch": 70,
                "pool_token_amount": "27021186773553930",
                "sui_amount": "27224408518954837"
            },
            {
                "epoch": 74,
                "pool_token_amount": "27022771200069581",
                "sui_amount": "27241110920426359"
            },
            {
                "epoch": 75,
                "pool_token_amount": "27023168083801906",
                "sui_amount": "27245112354168614"
            },
            {
                "epoch": 77,
                "pool_token_amount": "27014670037934885",
                "sui_amount": "27243746049149040"
            },
            {
                "epoch": 78,
                "pool_token_amount": "27015661847320965",
                "sui_amount": "27248349611117593"
            },
            {
                "epoch": 80,
                "pool_token_amount": "27012609692832604",
                "sui_amount": "27252478792628987"
            },
            {
                "epoch": 81,
                "pool_token_amount": "27013038766739749",
                "sui_amount": "27256718237080685"
            },
            {
                "epoch": 82,
                "pool_token_amount": "27013237275976076",
                "sui_amount": "27260524478115254"
            },
            {
                "epoch": 83,
                "pool_token_amount": "27013479310998602",
                "sui_amount": "27264375033245508"
            },
            {
                "epoch": 84,
                "pool_token_amount": "27013845127480386",
                "sui_amount": "27268350358397648"
            },
            {
                "epoch": 90,
                "pool_token_amount": "27015884314910346",
                "sui_amount": "27292174250428405"
            },
            {
                "epoch": 91,
                "pool_token_amount": "27016283752228417",
                "sui_amount": "27296219031074870"
            },
            {
                "epoch": 95,
                "pool_token_amount": "27017907191080417",
                "sui_amount": "27312699641903439"
            },
            {
                "epoch": 98,
                "pool_token_amount": "27019114272812603",
                "sui_amount": "27325150506372249"
            },
            {
                "epoch": 99,
                "pool_token_amount": "27019521840625265",
                "sui_amount": "27329272887906381"
            },
            {
                "epoch": 101,
                "pool_token_amount": "27020345744198071",
                "sui_amount": "27337536048701099"
            },
            {
                "epoch": 103,
                "pool_token_amount": "27021125988143623",
                "sui_amount": "27345801537389407"
            },
            {
                "epoch": 105,
                "pool_token_amount": "27021873744960050",
                "sui_amount": "27354089764623168"
            },
            {
                "epoch": 107,
                "pool_token_amount": "27022711310710498",
                "sui_amount": "27362519746889691"
            },
            {
                "epoch": 108,
                "pool_token_amount": "27023307246746105",
                "sui_amount": "27366835887606697"
            },
            {
                "epoch": 110,
                "pool_token_amount": "27024075099777728",
                "sui_amount": "27374838712886973"
            },
            {
                "epoch": 111,
                "pool_token_amount": "27024330081747657",
                "sui_amount": "27378347677208491"
            },
            {
                "epoch": 114,
                "pool_token_amount": "27025366152839520",
                "sui_amount": "27389145709991175"
            },
            {
                "epoch": 116,
                "pool_token_amount": "27025826079693872",
                "sui_amount": "27396110133858122"
            },
            {
                "epoch": 120,
                "pool_token_amount": "27027142208856486",
                "sui_amount": "27410442076120672"
            },
            {
                "epoch": 121,
                "pool_token_amount": "27027498180512796",
                "sui_amount": "27414052700987037"
            },
            {
                "epoch": 122,
                "pool_token_amount": "27027892661755307",
                "sui_amount": "27417703529158012"
            },
            {
                "epoch": 126,
                "pool_token_amount": "27029263100982765",
                "sui_amount": "27432097770497103"
            },
            {
                "epoch": 128,
                "pool_token_amount": "27029974981087125",
                "sui_amount": "27439323942776406"
            },
            {
                "epoch": 131,
                "pool_token_amount": "27031029367815716",
                "sui_amount": "27450157573019721"
            },
            {
                "epoch": 133,
                "pool_token_amount": "27031940716713989",
                "sui_amount": "27457588555905088"
            },
            {
                "epoch": 134,
                "pool_token_amount": "27033019934213097",
                "sui_amount": "27461936958859041"
            },
            {
                "epoch": 135,
                "pool_token_amount": "27033375535497738",
                "sui_amount": "27465549815580439"
            },
            {
                "epoch": 136,
                "pool_token_amount": "27032748058960303",
                "sui_amount": "27468163733437483"
            },
            {
                "epoch": 138,
                "pool_token_amount": "27033459682712452",
                "sui_amount": "27475395863964137"
            },
            {
                "epoch": 142,
                "pool_token_amount": "27034880875564637",
                "sui_amount": "27489844377017132"
            },
            {
                "epoch": 144,
                "pool_token_amount": "27035590897013279",
                "sui_amount": "27497065350079298"
            },
            {
                "epoch": 145,
                "pool_token_amount": "27035946168502143",
                "sui_amount": "27500679127964446"
            },
            {
                "epoch": 149,
                "pool_token_amount": "27041267722999767",
                "sui_amount": "27519365257416404"
            },
            {
                "epoch": 150,
                "pool_token_amount": "27041651826645344",
                "sui_amount": "27523094674363220"
            },
            {
                "epoch": 151,
                "pool_token_amount": "27042016196311250",
                "sui_amount": "27526803688084530"
            },
            {
                "epoch": 153,
                "pool_token_amount": "27042826093103557",
                "sui_amount": "27534304908944516"
            },
            {
                "epoch": 154,
                "pool_token_amount": "27043502918380301",
                "sui_amount": "27538332491817610"
            },
            {
                "epoch": 155,
                "pool_token_amount": "27044067430100644",
                "sui_amount": "27542245610994133"
            },
            {
                "epoch": 160,
                "pool_token_amount": "27045784517946125",
                "sui_amount": "27560684888657346"
            },
            {
                "epoch": 162,
                "pool_token_amount": "27046482311441912",
                "sui_amount": "27567887968996165"
            },
            {
                "epoch": 166,
                "pool_token_amount": "27047890103028430",
                "sui_amount": "27582313953676653"
            },
            {
                "epoch": 167,
                "pool_token_amount": "27048243974445277",
                "sui_amount": "27585923008343310"
            },
            {
                "epoch": 170,
                "pool_token_amount": "27100273636835846",
                "sui_amount": "27648203386350129"
            },
            {
                "epoch": 171,
                "pool_token_amount": "27100607708527304",
                "sui_amount": "27651612022316458"
            },
            {
                "epoch": 172,
                "pool_token_amount": "27100941686480243",
                "sui_amount": "27655020080086553"
            },
            {
                "epoch": 174,
                "pool_token_amount": "27101580037615980",
                "sui_amount": "27661625960337393"
            },
            {
                "epoch": 177,
                "pool_token_amount": "27185990086992814",
                "sui_amount": "27756735029545643"
            },
            {
                "epoch": 178,
                "pool_token_amount": "27186289059613619",
                "sui_amount": "27760022206446498"
            },
            {
                "epoch": 181,
                "pool_token_amount": "27207453590382431",
                "sui_amount": "27790583034784852"
            },
            {
                "epoch": 182,
                "pool_token_amount": "27207777894711324",
                "sui_amount": "27793895934880131"
            },
            {
                "epoch": 183,
                "pool_token_amount": "27207857259765351",
                "sui_amount": "27796958482034234"
            },
            {
                "epoch": 184,
                "pool_token_amount": "27214428614929516",
                "sui_amount": "27806655436699681"
            },
            {
                "epoch": 187,
                "pool_token_amount": "27215180143718543",
                "sui_amount": "27816478183481625"
            },
            {
                "epoch": 188,
                "pool_token_amount": "27215276361137721",
                "sui_amount": "27819564454945314"
            },
            {
                "epoch": 189,
                "pool_token_amount": "27215601353898702",
                "sui_amount": "27822886890628868"
            },
            {
                "epoch": 190,
                "pool_token_amount": "27215975102054486",
                "sui_amount": "27826258170478872"
            },
            {
                "epoch": 194,
                "pool_token_amount": "27217323083450385",
                "sui_amount": "27839621995957437"
            },
            {
                "epoch": 198,
                "pool_token_amount": "27223264223143166",
                "sui_amount": "27857686200972313"
            },
            {
                "epoch": 204,
                "pool_token_amount": "27245898338175897",
                "sui_amount": "27897641357081527"
            },
            {
                "epoch": 205,
                "pool_token_amount": "27246181318921517",
                "sui_amount": "27900638424817726"
            },
            {
                "epoch": 206,
                "pool_token_amount": "27246475353838221",
                "sui_amount": "27903649672924283"
            },
            {
                "epoch": 208,
                "pool_token_amount": "27247355076368153",
                "sui_amount": "27909969266469511"
            },
            {
                "epoch": 214,
                "pool_token_amount": "27271065461762420",
                "sui_amount": "27950740240510198"
            },
            {
                "epoch": 218,
                "pool_token_amount": "27295843932650333",
                "sui_amount": "27987277186720120"
            },
            {
                "epoch": 220,
                "pool_token_amount": "27334646531060288",
                "sui_amount": "28032635484247395"
            }
        ]
    },
    {
        "name": "QuantNode",
        "rates": [
            {
                "epoch": 1,
                "pool_token_amount": "20000000000000000",
                "sui_amount": "20000000000000000"
            },
            {
                "epoch": 5,
                "pool_token_amount": "20000000000008817",
                "sui_amount": "20000000000441000"
            },
            {
                "epoch": 7,
                "pool_token_amount": "20000000000008902",
                "sui_amount": "20000000000445300"
            },
            {
                "epoch": 10,
                "pool_token_amount": "20000000000008987",
                "sui_amount": "20000000000449600"
            },
            {
                "epoch": 14,
                "pool_token_amount": "20000000000010533",
                "sui_amount": "20000000000527000"
            },
            {
                "epoch": 15,
                "pool_token_amount": "20000000000010790",
                "sui_amount": "20000000000539900"
            },
            {
                "epoch": 16,
                "pool_token_amount": "20000000000140348",
                "sui_amount": "20000000007017893"
            },
            {
                "epoch": 17,
                "pool_token_amount": "20000000000246557",
                "sui_amount": "20000000012328401"
            },
            {
                "epoch": 23,
                "pool_token_amount": "20001190470087279",
                "sui_amount": "20015043495211770"
            },
            {
                "epoch": 24,
                "pool_token_amount": "20001278877477511",
                "sui_amount": "20019713178904400"
            },
            {
                "epoch": 26,
                "pool_token_amount": "20002347428849774",
                "sui_amount": "20028489960849676"
            },
            {
                "epoch": 27,
                "pool_token_amount": "20002790034527758",
                "sui_amount": "20032535617404197"
            },
            {
                "epoch": 32,
                "pool_token_amount": "26993471702404773",
                "sui_amount": "27054694043644871"
            },
            {
                "epoch": 33,
                "pool_token_amount": "26994051475202143",
                "sui_amount": "27059384431074923"
            },
            {
                "epoch": 35,
                "pool_token_amount": "26995021490536900",
                "sui_amount": "27068561226098944"
            },
            {
                "epoch": 36,
                "pool_token_amount": "26995435870948281",
                "sui_amount": "27072978018171919"
            },
            {
                "epoch": 37,
                "pool_token_amount": "26995859896355301",
                "sui_amount": "27077222051078338"
            },
            {
                "epoch": 38,
                "pool_token_amount": "26996281520545983",
                "sui_amount": "27081451594459345"
            },
            {
                "epoch": 39,
                "pool_token_amount": "26996691582657661",
                "sui_amount": "27085565714860988"
            },
            {
                "epoch": 40,
                "pool_token_amount": "26997211441934633",
                "sui_amount": "27089788534258292"
            },
            {
                "epoch": 43,
                "pool_token_amount": "26998941162758177",
                "sui_amount": "27102628393612395"
            },
            {
                "epoch": 45,
                "pool_token_amount": "26999770191521631",
                "sui_amount": "27110862227917756"
            },
            {
                "epoch": 46,
                "pool_token_amount": "27001560752615145",
                "sui_amount": "27116360966573045"
            },
            {
                "epoch": 48,
                "pool_token_amount": "27001360808233130",
                "sui_amount": "27123561730979871"
            },
            {
                "epoch": 49,
                "pool_token_amount": "27001791050724413",
                "sui_amount": "27127695217214753"
            },
            {
                "epoch": 50,
                "pool_token_amount": "27002200295045777",
                "sui_amount": "27131807303574819"
            },
            {
                "epoch": 51,
                "pool_token_amount": "27002609463593674",
                "sui_amount": "27135919189343523"
            },
            {
                "epoch": 53,
                "pool_token_amount": "27003429726485459",
                "sui_amount": "27144145998919972"
            },
            {
                "epoch": 57,
                "pool_token_amount": "27006284704480452",
                "sui_amount": "27161621732545730"
            },
            {
                "epoch": 58,
                "pool_token_amount": "27006697364303423",
                "sui_amount": "27165637616653630"
            },
            {
                "epoch": 62,
                "pool_token_amount": "27008289905212821",
                "sui_amount": "27181644059518491"
            },
            {
                "epoch": 64,
                "pool_token_amount": "27008090287201713",
                "sui_amount": "27188645010959747"
            },
            {
                "epoch": 65,
                "pool_token_amount": "27008487656074892",
                "sui_amount": "27192645794358896"
            },
            {
                "epoch": 68,
                "pool_token_amount": "27009778703078048",
                "sui_amount": "27205648023619041"
            },
            {
                "epoch": 73,
                "pool_token_amount": "27011856134462129",
                "sui_amount": "27226949264994893"
            },
            {
                "epoch": 74,
                "pool_token_amount": "27012266039212535",
                "sui_amount": "27231063514434596"
            },
            {
                "epoch": 75,
                "pool_token_amount": "27012662915016780",
                "sui_amount": "27235064948176851"
            },
            {
                "epoch": 78,
                "pool_token_amount": "27013930650453094",
                "sui_amount": "27247148038159528"
            },
            {
                "epoch": 80,
                "pool_token_amount": "27014684685477184",
                "sui_amount": "27255116716194683"
            },
            {
                "epoch": 82,
                "pool_token_amount": "27015518685246700",
                "sui_amount": "27263370644235871"
            },
            {
                "epoch": 86,
                "pool_token_amount": "27017052820401389",
                "sui_amount": "27279353698265701"
            },
            {
                "epoch": 87,
                "pool_token_amount": "27017452574548658",
                "sui_amount": "27283390584506424"
            },
            {
                "epoch": 88,
                "pool_token_amount": "27017852418455666",
                "sui_amount": "27287428914813513"
            },
            {
                "epoch": 91,
                "pool_token_amount": "27019043014821838",
                "sui_amount": "27299547583990550"
            },
            {
                "epoch": 93,
                "pool_token_amount": "27019845685944340",
                "sui_amount": "27307668257664995"
            },
            {
                "epoch": 95,
                "pool_token_amount": "27020668444532791",
                "sui_amount": "27316030239456262"
            },
            {
                "epoch": 99,
                "pool_token_amount": "27022310970765038",
                "sui_amount": "27332631663794315"
            },
            {
                "epoch": 102,
                "pool_token_amount": "27023559067487466",
                "sui_amount": "27345259385703128"
            },
            {
                "epoch": 109,
                "pool_token_amount": "27026064025983141",
                "sui_amount": "27373981319340064"
            },
            {
                "epoch": 110,
                "pool_token_amount": "27026470167206828",
                "sui_amount": "27378005553916819"
            },
            {
                "epoch": 113,
                "pool_token_amount": "27027488362219339",
                "sui_amount": "27388786680788512"
            },
            {
                "epoch": 115,
                "pool_token_amount": "27028202725973182",
                "sui_amount": "27396009092377394"
            },
            {
                "epoch": 116,
                "pool_token_amount": "27028366077902264",
                "sui_amount": "27399423858287130"
            },
            {
                "epoch": 117,
                "pool_token_amount": "27028726577097304",
                "sui_amount": "27403038270963458"
            },
            {
                "epoch": 118,
                "pool_token_amount": "27029082610351882",
                "sui_amount": "27406648333877442"
            },
            {
                "epoch": 119,
                "pool_token_amount": "27029438664773628",
                "sui_amount": "27410259039251653"
            },
            {
                "epoch": 120,
                "pool_token_amount": "27029794688786512",
                "sui_amount": "27413869864191389"
            },
            {
                "epoch": 124,
                "pool_token_amount": "27042784692751933",
                "sui_amount": "27440051343019778"
            },
            {
                "epoch": 125,
                "pool_token_amount": "27043013946484426",
                "sui_amount": "27443534972742359"
            },
            {
                "epoch": 126,
                "pool_token_amount": "27043272039542806",
                "sui_amount": "27447047515496885"
            },
            {
                "epoch": 130,
                "pool_token_amount": "27033110918164541",
                "sui_amount": "27449748567997737"
            },
            {
                "epoch": 131,
                "pool_token_amount": "27033506235404277",
                "sui_amount": "27453403137582519"
            },
            {
                "epoch": 138,
                "pool_token_amount": "27036330883070778",
                "sui_amount": "27479047711490971"
            },
            {
                "epoch": 144,
                "pool_token_amount": "27049652614309482",
                "sui_amount": "27512095197606132"
            },
            {
                "epoch": 145,
                "pool_token_amount": "27050007876419024",
                "sui_amount": "27515708975491280"
            },
            {
                "epoch": 148,
                "pool_token_amount": "27051092652392961",
                "sui_amount": "27526746132210402"
            },
            {
                "epoch": 149,
                "pool_token_amount": "27053398739410541",
                "sui_amount": "27532431488476590"
            },
            {
                "epoch": 153,
                "pool_token_amount": "27054873306438337",
                "sui_amount": "27547285860004702"
            },
            {
                "epoch": 154,
                "pool_token_amount": "27055372174060122",
                "sui_amount": "27551132223868984"
            },
            {
                "epoch": 155,
                "pool_token_amount": "27055736368186019",
                "sui_amount": "27554841344744369"
            },
            {
                "epoch": 157,
                "pool_token_amount": "27056462570033452",
                "sui_amount": "27562256673518819"
            },
            {
                "epoch": 158,
                "pool_token_amount": "27056826609565841",
                "sui_amount": "27565965567767206"
            },
            {
                "epoch": 161,
                "pool_token_amount": "27057881837702683",
                "sui_amount": "27576965094759039"
            },
            {
                "epoch": 162,
                "pool_token_amount": "27058236435372960",
                "sui_amount": "27580570521358836"
            },
            {
                "epoch": 163,
                "pool_token_amount": "27058590379361670",
                "sui_amount": "27584178708123104"
            },
            {
                "epoch": 168,
                "pool_token_amount": "27058397474345028",
                "sui_amount": "27600040955332501"
            },
            {
                "epoch": 171,
                "pool_token_amount": "27059401926453862",
                "sui_amount": "27610270811469728"
            },
            {
                "epoch": 175,
                "pool_token_amount": "27060708136158340",
                "sui_amount": "27623602429450475"
            },
            {
                "epoch": 181,
                "pool_token_amount": "27063851887147976",
                "sui_amount": "27644698997678157"
            },
            {
                "epoch": 183,
                "pool_token_amount": "27064500423025451",
                "sui_amount": "27651324606034429"
            },
            {
                "epoch": 190,
                "pool_token_amount": "27066584739306444",
                "sui_amount": "27674369006559272"
            },
            {
                "epoch": 192,
                "pool_token_amount": "27067235506881265",
                "sui_amount": "27681023867411954"
            },
            {
                "epoch": 197,
                "pool_token_amount": "27069791589938922",
                "sui_amount": "27698628291993546"
            },
            {
                "epoch": 199,
                "pool_token_amount": "27070453587385782",
                "sui_amount": "27705286132116847"
            },
            {
                "epoch": 202,
                "pool_token_amount": "27071459360263241",
                "sui_amount": "27714709330572546"
            },
            {
                "epoch": 204,
                "pool_token_amount": "27071093905951783",
                "sui_amount": "27719739913722022"
            },
            {
                "epoch": 205,
                "pool_token_amount": "27071387650210948",
                "sui_amount": "27722748014397819"
            },
            {
                "epoch": 206,
                "pool_token_amount": "27071681673258137",
                "sui_amount": "27725759262504376"
            },
            {
                "epoch": 207,
                "pool_token_amount": "27070834165074770",
                "sui_amount": "27727601249465937"
            },
            {
                "epoch": 208,
                "pool_token_amount": "27071127964928807",
                "sui_amount": "27730610800038844"
            },
            {
                "epoch": 209,
                "pool_token_amount": "27071421841861979",
                "sui_amount": "27733621433574857"
            },
            {
                "epoch": 210,
                "pool_token_amount": "27071710549440192",
                "sui_amount": "27736624560338219"
            },
            {
                "epoch": 213,
                "pool_token_amount": "27072751222040350",
                "sui_amount": "27745802033254234"
            },
            {
                "epoch": 215,
                "pool_token_amount": "27073336862293796",
                "sui_amount": "27751804872768677"
            },
            {
                "epoch": 216,
                "pool_token_amount": "27073629608743190",
                "sui_amount": "27754805975559067"
            },
            {
                "epoch": 217,
                "pool_token_amount": "27073922328829704",
                "sui_amount": "27757807100095073"
            },
            {
                "epoch": 220,
                "pool_token_amount": "27074795158835999",
                "sui_amount": "27766803523261606"
            },
            {
                "epoch": 221,
                "pool_token_amount": "27075087795303257",
                "sui_amount": "27769804957779698"
            },
            {
                "epoch": 223,
                "pool_token_amount": "27075346017277258",
                "sui_amount": "27775472538425194"
            },
            {
                "epoch": 224,
                "pool_token_amount": "26939975683169656",
                "sui_amount": "27639302064478117"
            }
        ]
    },
    {
        "name": "P2P.ORG",
        "rates": [
            {
                "epoch": 0,
                "pool_token_amount": "0",
                "sui_amount": "0"
            },
            {
                "epoch": 1,
                "pool_token_amount": "25000000000000000",
                "sui_amount": "25000000000000000"
            },
            {
                "epoch": 2,
                "pool_token_amount": "25000000000000000",
                "sui_amount": "25000000000550800"
            },
            {
                "epoch": 8,
                "pool_token_amount": "25000000000000000",
                "sui_amount": "25000000000577800"
            },
            {
                "epoch": 19,
                "pool_token_amount": "25000000000000000",
                "sui_amount": "25000000019836964"
            },
            {
                "epoch": 20,
                "pool_token_amount": "25000000000000000",
                "sui_amount": "25000000032208364"
            },
            {
                "epoch": 23,
                "pool_token_amount": "25030656722899593",
                "sui_amount": "25048370994433130"
            },
            {
                "epoch": 24,
                "pool_token_amount": "25045377211693528",
                "sui_amount": "25069117160534757"
            },
            {
                "epoch": 29,
                "pool_token_amount": "35086229904556240",
                "sui_amount": "35153066057563791"
            },
            {
                "epoch": 30,
                "pool_token_amount": "35087408140840125",
                "sui_amount": "35159752689687761"
            },
            {
                "epoch": 32,
                "pool_token_amount": "35088314144518218",
                "sui_amount": "35171465924337027"
            },
            {
                "epoch": 36,
                "pool_token_amount": "35090525318592443",
                "sui_amount": "35195002509733582"
            },
            {
                "epoch": 37,
                "pool_token_amount": "35091140691570459",
                "sui_amount": "35200644447289464"
            },
            {
                "epoch": 41,
                "pool_token_amount": "35092424462875933",
                "sui_amount": "35221748177058251"
            },
            {
                "epoch": 42,
                "pool_token_amount": "35092958037959521",
                "sui_amount": "35227185584149274"
            },
            {
                "epoch": 46,
                "pool_token_amount": "35095307685875763",
                "sui_amount": "35248749163291111"
            },
            {
                "epoch": 49,
                "pool_token_amount": "35085358509259351",
                "sui_amount": "35253157328816786"
            },
            {
                "epoch": 51,
                "pool_token_amount": "35086420107864466",
                "sui_amount": "35263826265629940"
            },
            {
                "epoch": 53,
                "pool_token_amount": "35087480527576910",
                "sui_amount": "35274495285735541"
            },
            {
                "epoch": 56,
                "pool_token_amount": "35089188620600728",
                "sui_amount": "35290717854026524"
            },
            {
                "epoch": 59,
                "pool_token_amount": "35092020461907311",
                "sui_amount": "35307970852605426"
            },
            {
                "epoch": 60,
                "pool_token_amount": "35092700596751841",
                "sui_amount": "35313455985824558"
            },
            {
                "epoch": 62,
                "pool_token_amount": "35094155028242909",
                "sui_amount": "35324523339277213"
            },
            {
                "epoch": 64,
                "pool_token_amount": "35095654822793532",
                "sui_amount": "35335635512230172"
            },
            {
                "epoch": 67,
                "pool_token_amount": "35099307570408625",
                "sui_amount": "35354116914914077"
            },
            {
                "epoch": 69,
                "pool_token_amount": "35101408355847458",
                "sui_amount": "35366235229697407"
            },
            {
                "epoch": 71,
                "pool_token_amount": "35102512628430922",
                "sui_amount": "35377354688351044"
            },
            {
                "epoch": 72,
                "pool_token_amount": "35103460779886624",
                "sui_amount": "35383311791158349"
            },
            {
                "epoch": 74,
                "pool_token_amount": "35107285954885047",
                "sui_amount": "35397070696036764"
            },
            {
                "epoch": 80,
                "pool_token_amount": "35094205217390299",
                "sui_amount": "35412693470042699"
            },
            {
                "epoch": 81,
                "pool_token_amount": "225341601681707308",
                "sui_amount": "227418147227344030"
            },
            {
                "epoch": 82,
                "pool_token_amount": "225344903853984477",
                "sui_amount": "227452230235124151"
            },
            {
                "epoch": 83,
                "pool_token_amount": "225348992579373152",
                "sui_amount": "227487110537400031"
            },
            {
                "epoch": 85,
                "pool_token_amount": "225351551250794161",
                "sui_amount": "227551297911497604"
            },
            {
                "epoch": 89,
                "pool_token_amount": "225366688318660085",
                "sui_amount": "227690406179096068"
            },
            {
                "epoch": 90,
                "pool_token_amount": "225370100710144188",
                "sui_amount": "227724886633701053"
            },
            {
                "epoch": 91,
                "pool_token_amount": "225373503600692252",
                "sui_amount": "227759275783756138"
            },
            {
                "epoch": 93,
                "pool_token_amount": "225379981948580898",
                "sui_amount": "227828056535015061"
            },
            {
                "epoch": 98,
                "pool_token_amount": "284813408495757562",
                "sui_amount": "288106658303800354"
            },
            {
                "epoch": 99,
                "pool_token_amount": "284817822744733955",
                "sui_amount": "288151317415176764"
            },
            {
                "epoch": 100,
                "pool_token_amount": "284822240451955330",
                "sui_amount": "288196008750488598"
            },
            {
                "epoch": 101,
                "pool_token_amount": "284826702495415625",
                "sui_amount": "288240894021778068"
            },
            {
                "epoch": 102,
                "pool_token_amount": "284831151829094437",
                "sui_amount": "288285892793695342"
            },
            {
                "epoch": 105,
                "pool_token_amount": "284845189486402309",
                "sui_amount": "288422395462941486"
            },
            {
                "epoch": 106,
                "pool_token_amount": "284849825940752169",
                "sui_amount": "288467953878970605"
            },
            {
                "epoch": 112,
                "pool_token_amount": "284876508475425537",
                "sui_amount": "288723576450062383"
            },
            {
                "epoch": 113,
                "pool_token_amount": "284812946488579765",
                "sui_amount": "288694358835989253"
            },
            {
                "epoch": 115,
                "pool_token_amount": "284823838712931261",
                "sui_amount": "288775800448343850"
            },
            {
                "epoch": 116,
                "pool_token_amount": "284828460183233986",
                "sui_amount": "288815685723464798"
            },
            {
                "epoch": 117,
                "pool_token_amount": "284832509545270569",
                "sui_amount": "288854988916870947"
            },
            {
                "epoch": 119,
                "pool_token_amount": "284840671450151446",
                "sui_amount": "288933579801905464"
            },
            {
                "epoch": 120,
                "pool_token_amount": "284849126063522005",
                "sui_amount": "288977272217509299"
            },
            {
                "epoch": 121,
                "pool_token_amount": "284852994504290249",
                "sui_amount": "289016310521043611"
            },
            {
                "epoch": 122,
                "pool_token_amount": "284858461218800800",
                "sui_amount": "289056983067748630"
            },
            {
                "epoch": 125,
                "pool_token_amount": "284492029907874886",
                "sui_amount": "288790448383069956"
            },
            {
                "epoch": 127,
                "pool_token_amount": "283957115659100231",
                "sui_amount": "288317461155267926"
            },
            {
                "epoch": 128,
                "pool_token_amount": "283961854833854496",
                "sui_amount": "288357327637111374"
            },
            {
                "epoch": 129,
                "pool_token_amount": "283970381577575968",
                "sui_amount": "288401067611510260"
            },
            {
                "epoch": 131,
                "pool_token_amount": "283979384195112947",
                "sui_amount": "288480355869737383"
            },
            {
                "epoch": 133,
                "pool_token_amount": "283984732808343694",
                "sui_amount": "288556084081784830"
            },
            {
                "epoch": 135,
                "pool_token_amount": "283906834915618491",
                "sui_amount": "288634218721917840"
            },
            {
                "epoch": 136,
                "pool_token_amount": "283918717798690755",
                "sui_amount": "288681343656081675"
            },
            {
                "epoch": 138,
                "pool_token_amount": "283934525975436670",
                "sui_amount": "288767571538732592"
            },
            {
                "epoch": 139,
                "pool_token_amount": "283937885723380482",
                "sui_amount": "288806048453616593"
            },
            {
                "epoch": 140,
                "pool_token_amount": "283944546326174875",
                "sui_amount": "288847859266574580"
            },
            {
                "epoch": 141,
                "pool_token_amount": "283958438005597010",
                "sui_amount": "288897112272647680"
            },
            {
                "epoch": 145,
                "pool_token_amount": "283992250092456450",
                "sui_amount": "289072006943940585"
            },
            {
                "epoch": 148,
                "pool_token_amount": "284017178525462232",
                "sui_amount": "289202953612938816"
            },
            {
                "epoch": 152,
                "pool_token_amount": "228700733022766608",
                "sui_amount": "232997551630969843"
            },
            {
                "epoch": 154,
                "pool_token_amount": "228709804451722830",
                "sui_amount": "233063998755268384"
            },
            {
                "epoch": 157,
                "pool_token_amount": "228715040372659305",
                "sui_amount": "233155130173266768"
            },
            {
                "epoch": 159,
                "pool_token_amount": "228728722043871235",
                "sui_amount": "233226276807079287"
            },
            {
                "epoch": 162,
                "pool_token_amount": "228060519700181068",
                "sui_amount": "232628734485942527"
            },
            {
                "epoch": 163,
                "pool_token_amount": "228063512468797756",
                "sui_amount": "232659480398663754"
            },
            {
                "epoch": 167,
                "pool_token_amount": "228071667066425715",
                "sui_amount": "232778589346315107"
            },
            {
                "epoch": 168,
                "pool_token_amount": "228071880122863949",
                "sui_amount": "232804789310528571"
            },
            {
                "epoch": 170,
                "pool_token_amount": "227752794905867483",
                "sui_amount": "232531250118201104"
            },
            {
                "epoch": 171,
                "pool_token_amount": "227758701177796422",
                "sui_amount": "232563447283275795"
            },
            {
                "epoch": 173,
                "pool_token_amount": "227737573234046770",
                "sui_amount": "232593653106806548"
            },
            {
                "epoch": 174,
                "pool_token_amount": "227740255886362931",
                "sui_amount": "232622107499569062"
            },
            {
                "epoch": 179,
                "pool_token_amount": "226750904187754501",
                "sui_amount": "231739874260561910"
            },
            {
                "epoch": 183,
                "pool_token_amount": "226757068218445818",
                "sui_amount": "231848813216505836"
            },
            {
                "epoch": 184,
                "pool_token_amount": "226663096876465472",
                "sui_amount": "231778400449148566"
            },
            {
                "epoch": 186,
                "pool_token_amount": "226671774281094782",
                "sui_amount": "231838711257282371"
            },
            {
                "epoch": 187,
                "pool_token_amount": "226674507373312220",
                "sui_amount": "231867217033124696"
            },
            {
                "epoch": 188,
                "pool_token_amount": "226682117962658091",
                "sui_amount": "231900716823062979"
            },
            {
                "epoch": 192,
                "pool_token_amount": "223892703493438990",
                "sui_amount": "229148957541143384"
            },
            {
                "epoch": 193,
                "pool_token_amount": "223895507540331748",
                "sui_amount": "229177173466517001"
            },
            {
                "epoch": 195,
                "pool_token_amount": "223690042955788900",
                "sui_amount": "229017555524654420"
            },
            {
                "epoch": 197,
                "pool_token_amount": "223575014537139015",
                "sui_amount": "228950477444671072"
            },
            {
                "epoch": 199,
                "pool_token_amount": "223580524048336714",
                "sui_amount": "229006681529676999"
            },
            {
                "epoch": 200,
                "pool_token_amount": "223583268765963380",
                "sui_amount": "229034797925539223"
            },
            {
                "epoch": 203,
                "pool_token_amount": "223589937143527891",
                "sui_amount": "229110109941055395"
            },
            {
                "epoch": 204,
                "pool_token_amount": "223592412303418523",
                "sui_amount": "229135521025963508"
            },
            {
                "epoch": 205,
                "pool_token_amount": "223594964971301885",
                "sui_amount": "229161026133909368"
            },
            {
                "epoch": 208,
                "pool_token_amount": "223597941130789735",
                "sui_amount": "229232801809884287"
            },
            {
                "epoch": 210,
                "pool_token_amount": "223472689911840674",
                "sui_amount": "229150179130517017"
            },
            {
                "epoch": 219,
                "pool_token_amount": "223515172673818233",
                "sui_amount": "229400017498415488"
            },
            {
                "epoch": 220,
                "pool_token_amount": "223517644338068947",
                "sui_amount": "229425387403734830"
            },
            {
                "epoch": 222,
                "pool_token_amount": "223473323312697903",
                "sui_amount": "229425733569810032"
            }
        ]
    }
]